setuptools_yaml
