Metadata-Version: 1.0
Name: setuptools-yaml
Version: 0.4
Summary: Use YAML file for your project metadata
Home-page: https://github.com/sudarkoff/setuptools-yaml
Author: George Sudarkoff
Author-email: george@sudarkoff.com
License: MIT
Keywords: distutils setuptools metadata yaml
Platform: UNKNOWN
